gempa_terkini_BMKG/__init__.py
gempa_terkini_BMKG/gempaTerkini.py
muzadash-0.0.4.dist-info/LICENSE
muzadash-0.0.4.dist-info/METADATA
muzadash-0.0.4.dist-info/WHEEL
muzadash-0.0.4.dist-info/top_level.txt
muzadash-0.0.4.dist-info/RECORD
