Metadata-Version: 2.1
Name: muzadash
Version: 0.0.4
Summary: This package will get the lates Dashboard Monitoring Indonesia
Home-page: https://github.com/Insan-Nusantara-Tecnology/latest-indonesia-earthquake
Author: Fikri Muzadi
Author-email: fikrimuzadi@gmail.com
Classifier: Programming Language :: Python :: 3
Classifier: License :: OSI Approved :: GNU General Public License v3 (GPLv3)
Classifier: Operating System :: OS Independent
Classifier: Development Status :: 4 - Beta
Requires-Python: >=3.6
License-File: LICENSE
Requires-Dist: requests
Requires-Dist: beautifulsoup4
